{
  "configurations": [
    {
      "directories": [
        {
          "build": ".",
          "minimumCMakeVersion": {
            "string": "3.4.1"
          },
          "projectIndex": 0,
          "source": ".",
          "targetIndexes": [
            0
          ]
        }
      ],
      "name": "RelWithDebInfo",
      "projects": [
        {
          "directoryIndexes": [
            0
          ],
          "name": "Project",
          "targetIndexes": [
            0
          ]
        }
      ],
      "targets": [
        {
          "directoryIndex": 0,
          "id": "native-lib::@6890427a1f51a3e7e1df",
          "jsonFile": "target-native-lib-RelWithDebInfo-32301ebe20d63e0457a8.json",
          "name": "native-lib",
          "projectIndex": 0
        }
      ]
    }
  ],
  "kind": "codemodel",
  "paths": {
    "build": "/Users/steve/AndroidStudioProjects/BaseArchitecture/core/network/.cxx/RelWithDebInfo/1d6o5x2f/x86",
    "source": "/Users/steve/AndroidStudioProjects/BaseArchitecture/core/network"
  },
  "version": {
    "major": 2,
    "minor": 1
  }
}
